agton/wallet/__init__.py
agton/wallet/mnemonic.py
agton/wallet/wallet_v3r2.py
agton/wallet/wallet_v4r2.py
agton/wallet/wallet_v5.py
agton_wallet-0.2.4.dist-info/licenses/LICENSE
agton_wallet-0.2.4.dist-info/METADATA
agton_wallet-0.2.4.dist-info/WHEEL
agton_wallet-0.2.4.dist-info/top_level.txt
agton_wallet-0.2.4.dist-info/RECORD
